LICENSE
README.md
setup.py
src/aws_ssm_copy/__init__.py
src/aws_ssm_copy/__main__.py
src/aws_ssm_copy/ssm_copy.py
src/aws_ssm_copy.egg-info/PKG-INFO
src/aws_ssm_copy.egg-info/SOURCES.txt
src/aws_ssm_copy.egg-info/dependency_links.txt
src/aws_ssm_copy.egg-info/entry_points.txt
src/aws_ssm_copy.egg-info/not-zip-safe
src/aws_ssm_copy.egg-info/requires.txt
src/aws_ssm_copy.egg-info/top_level.txt