Metadata-Version: 2.1
Name: aws-ssm-copy
Version: 0.4.0
Summary: Copy AWS Parameter Store parameters
Home-page: https://github.com/binxio/aws-ssm-copy
Author: Mark van Holsteijn
Author-email: markvanholsteijn@binx.io
License: UNKNOWN
Platform: any
License-File: LICENSE
